django_workflow_fsm-4.0.1.dist-info/DESCRIPTION.rst
django_workflow_fsm-4.0.1.dist-info/METADATA
django_workflow_fsm-4.0.1.dist-info/RECORD
django_workflow_fsm-4.0.1.dist-info/WHEEL
django_workflow_fsm-4.0.1.dist-info/metadata.json
django_workflow_fsm-4.0.1.dist-info/top_level.txt
workflow/__init__.py
workflow/apps.py
workflow/choices.py
workflow/filters.py
workflow/fsm.py
workflow/models.py
workflow/receivers.py
workflow/rest.py
workflow/serializers.py
workflow/signals.py
workflow/task_runner.py
workflow/tasks.py
workflow/urls.py
workflow/views.py
workflow/viewsets.py
workflow/migrations/0001_initial.py
workflow/migrations/__init__.py
