Metadata-Version: 2.0
Name: django-workflow-fsm
Version: 4.0.1
Summary: Control FSMs from Django
Home-page: https://github.com/george-silva/django-workflow-fsm
Author: George Silva
Author-email: george@sigmageosistemas.com.br
License: MIT
Keywords: django-workflow-fsm
Platform: UNKNOWN
Classifier: Development Status :: 3 - Alpha
Classifier: Framework :: Django
Classifier: Framework :: Django :: 1.8
Classifier: Framework :: Django :: 1.9
Classifier: Framework :: Django :: 1.10
Classifier: Intended Audience :: Developers
Classifier: License :: OSI Approved :: BSD License
Classifier: Natural Language :: English
Classifier: Programming Language :: Python :: 2
Classifier: Programming Language :: Python :: 2.7
Classifier: Programming Language :: Python :: 3
Classifier: Programming Language :: Python :: 3.3
Classifier: Programming Language :: Python :: 3.4
Classifier: Programming Language :: Python :: 3.5
Requires-Dist: celery
Requires-Dist: django
Requires-Dist: django-common-models
Requires-Dist: django-ordered-model
Requires-Dist: django-reversion
Requires-Dist: djangorestframework
Requires-Dist: djangorestframework-filters
Requires-Dist: jsonfield
Requires-Dist: redis
